odoo/addons/edi_ediversa_oca_sale_order_import/README.rst
odoo/addons/edi_ediversa_oca_sale_order_import/__init__.py
odoo/addons/edi_ediversa_oca_sale_order_import/__manifest__.py
odoo/addons/edi_ediversa_oca_sale_order_import/components/__init__.py
odoo/addons/edi_ediversa_oca_sale_order_import/components/ediversa_api.py
odoo/addons/edi_ediversa_oca_sale_order_import/components/ediversa_process_sale_order.py
odoo/addons/edi_ediversa_oca_sale_order_import/components/ediversa_receive_sale_order.py
odoo/addons/edi_ediversa_oca_sale_order_import/data/edi.xml
odoo/addons/edi_ediversa_oca_sale_order_import/data/ir_cron.xml
odoo/addons/edi_ediversa_oca_sale_order_import/i18n/edi_ediversa_oca_sale_order_import.pot
odoo/addons/edi_ediversa_oca_sale_order_import/i18n/it.po
odoo/addons/edi_ediversa_oca_sale_order_import/models/__init__.py
odoo/addons/edi_ediversa_oca_sale_order_import/models/edi_exchange_record.py
odoo/addons/edi_ediversa_oca_sale_order_import/readme/CONFIGURE.md
odoo/addons/edi_ediversa_oca_sale_order_import/readme/CONTRIBUTORS.md
odoo/addons/edi_ediversa_oca_sale_order_import/readme/DESCRIPTION.md
odoo/addons/edi_ediversa_oca_sale_order_import/readme/USAGE.md
odoo/addons/edi_ediversa_oca_sale_order_import/static/description/icon.png
odoo/addons/edi_ediversa_oca_sale_order_import/static/description/index.html
odoo/addons/edi_ediversa_oca_sale_order_import/tests/__init__.py
odoo/addons/edi_ediversa_oca_sale_order_import/tests/test_edi_ediversa_sale_order_import.py
odoo/addons/edi_ediversa_oca_sale_order_import/tests/sale_order_docs/ediversa_sale_order_existing_partner.txt
odoo/addons/edi_ediversa_oca_sale_order_import/tests/sale_order_docs/ediversa_sale_order_new_partner.txt
odoo_addon_edi_ediversa_oca_sale_order_import-17.0.1.0.0.6.dist-info/METADATA
odoo_addon_edi_ediversa_oca_sale_order_import-17.0.1.0.0.6.dist-info/WHEEL
odoo_addon_edi_ediversa_oca_sale_order_import-17.0.1.0.0.6.dist-info/top_level.txt
odoo_addon_edi_ediversa_oca_sale_order_import-17.0.1.0.0.6.dist-info/RECORD
